setup.cfg
setup.py
helper_viMap/__init__.py
helper_viMap/helper_viMap.py
helper_viMap.egg-info/PKG-INFO
helper_viMap.egg-info/SOURCES.txt
helper_viMap.egg-info/dependency_links.txt
helper_viMap.egg-info/not-zip-safe
helper_viMap.egg-info/top_level.txt