Metadata-Version: 1.0
Name: helper-viMap
Version: 1.1
Summary: Contains all fonction you need for the use of viMap pluggins
Home-page: UNKNOWN
Author: UNKNOWN
Author-email: betsalel.eliasaph.lahoutou@railenium.eu
License: UNKNOWN
Platform: UNKNOWN
